bs_solevaluator
